odoo/addons/datev_export_xml/README.rst
odoo/addons/datev_export_xml/__init__.py
odoo/addons/datev_export_xml/__manifest__.py
odoo/addons/datev_export_xml/data/ir_cron_data.xml
odoo/addons/datev_export_xml/demo/export_data.xml
odoo/addons/datev_export_xml/i18n/datev_export_xml.pot
odoo/addons/datev_export_xml/i18n/de.po
odoo/addons/datev_export_xml/models/__init__.py
odoo/addons/datev_export_xml/models/account_move.py
odoo/addons/datev_export_xml/models/datev_export.py
odoo/addons/datev_export_xml/models/datev_pdf_generator.py
odoo/addons/datev_export_xml/models/datev_xml_generator.py
odoo/addons/datev_export_xml/models/datev_zip_generator.py
odoo/addons/datev_export_xml/models/res_company.py
odoo/addons/datev_export_xml/models/res_config_settings.py
odoo/addons/datev_export_xml/readme/CONFIGURATION.md
odoo/addons/datev_export_xml/readme/CONTRIBUTORS.md
odoo/addons/datev_export_xml/readme/DESCRIPTION.md
odoo/addons/datev_export_xml/readme/USAGE.md
odoo/addons/datev_export_xml/security/groups.xml
odoo/addons/datev_export_xml/security/ir.model.access.csv
odoo/addons/datev_export_xml/security/security.xml
odoo/addons/datev_export_xml/static/description/belegtransfer_belege_hochladen.png
odoo/addons/datev_export_xml/static/description/belegtransfer_belege_hochladen_dateiauswahl.png
odoo/addons/datev_export_xml/static/description/belegtransfer_protokoll_auswahl.png
odoo/addons/datev_export_xml/static/description/belegtransfer_protokoll_details.png
odoo/addons/datev_export_xml/static/description/belegtransfer_protokoll_liste.png
odoo/addons/datev_export_xml/static/description/belegtransfer_protokoll_timestamp.png
odoo/addons/datev_export_xml/static/description/belegtransfer_verezcihnis_anlegen_2.png
odoo/addons/datev_export_xml/static/description/belegtransfer_verzeichnis_anlegen_0.png
odoo/addons/datev_export_xml/static/description/belegtransfer_verzeichnis_anlegen_1.png
odoo/addons/datev_export_xml/static/description/belegtransfer_verzeichnis_anlegen_3.png
odoo_addon_datev_export_xml-17.0.1.0.1.dist-info/METADATA
odoo_addon_datev_export_xml-17.0.1.0.1.dist-info/WHEEL
odoo_addon_datev_export_xml-17.0.1.0.1.dist-info/top_level.txt
odoo_addon_datev_export_xml-17.0.1.0.1.dist-info/RECORD
