Metadata-Version: 2.1
Name: odoo-addon-datev_export_xml
Version: 17.0.1.0.1
Requires-Python: >=3.10
Requires-Dist: odoo-addon-datev_export>=17.0dev,<17.1dev
Requires-Dist: odoo>=17.0a,<17.1dev
Summary: Export invoices and refunds as xml and pdf files zipped in DATEV format.
Home-page: https://github.com/OCA/l10n-germany
License: AGPL-3
Author: Guenter Selbert, Thorsten Vocks, Maciej Wichowski, Daniela Scarpa, Maria Sparenberg, initOS GmbH, Jan Sierpina, Odoo Community Association (OCA)
Author-email: support@odoo-community.org
Classifier: Programming Language :: Python
Classifier: Framework :: Odoo
Classifier: Framework :: Odoo :: 17.0
Classifier: License :: OSI Approved :: GNU Affero General Public License v3
